py_virion_data/__about__.py
py_virion_data/__init__.py
py_virion_data/deposit.py
py_virion_data/get_json.py
py_virion_data/sanitize_id.py
py_virion_data-0.1.1.dist-info/METADATA
py_virion_data-0.1.1.dist-info/WHEEL
py_virion_data-0.1.1.dist-info/licenses/LICENSE.txt
py_virion_data-0.1.1.dist-info/RECORD
